tappack/__init__.py
tappack/autoexec.be.template
tappack/constants.py
tappack/packaging.py
tappack/patch.py
tappack/server.py
tappack/source.py
tappack/tunnel.py
tappack/version
tappack-0.3.2.dist-info/METADATA
tappack-0.3.2.dist-info/WHEEL
tappack-0.3.2.dist-info/entry_points.txt
tappack-0.3.2.dist-info/top_level.txt
tappack-0.3.2.dist-info/RECORD
