Metadata-Version: 2.1
Name: tappack
Version: 0.3.2
Summary: A packager for Tasmota Berry Application (TAPP) apps
Home-page: https://link.frontmatter.ai/tappack
Author: Frontmatter
License: Copyright © 2023 Frontmatter. All rights reserved.
Keywords: development berry script tasmota tapp
Platform: UNKNOWN
Requires-Dist: click
Requires-Dist: pyyaml
Requires-Dist: requests
Provides-Extra: server
Requires-Dist: flask ; extra == 'server'
Requires-Dist: pyngrok ; extra == 'server'
